mistermarket/__init__.py
mistermarket/mistermarket.py
mistermarket-0.1.2.dist-info/LICENSE
mistermarket-0.1.2.dist-info/METADATA
mistermarket-0.1.2.dist-info/WHEEL
mistermarket-0.1.2.dist-info/top_level.txt
mistermarket-0.1.2.dist-info/RECORD
