Metadata-Version: 2.1
Name: mistermarket
Version: 0.1.2
Summary: Mr. Market - your servant in the Philippine financial market
Home-page: https://github.com/jerobado/mistermarket
Author: Jero Bado
Author-email: gerol.bado@geronacapital.com
License: UNKNOWN
Platform: UNKNOWN
Classifier: Programming Language :: Python :: 3
Classifier: License :: OSI Approved :: GNU General Public License v3 (GPLv3)
Classifier: Operating System :: OS Independent
Requires-Python: >=3.6
